MANIFEST.in
README.md
README.rst
setup.py
mezzanine_pubsubhubbub_pub/__init__.py
mezzanine_pubsubhubbub_pub/defaults.py
mezzanine_pubsubhubbub_pub/feeds.py
mezzanine_pubsubhubbub_pub/models.py
mezzanine_pubsubhubbub_pub/urls.py
mezzanine_pubsubhubbub_pub/views.py
mezzanine_pubsubhubbub_pub.egg-info/PKG-INFO
mezzanine_pubsubhubbub_pub.egg-info/SOURCES.txt
mezzanine_pubsubhubbub_pub.egg-info/dependency_links.txt
mezzanine_pubsubhubbub_pub.egg-info/not-zip-safe
mezzanine_pubsubhubbub_pub.egg-info/requires.txt
mezzanine_pubsubhubbub_pub.egg-info/top_level.txt
tests/__init__.py
tests/settings.py
tests/tests.py
tests/urls.py